azure/mgmt/datalake/analytics/__init__.py
azure/mgmt/datalake/analytics/version.py
azure/mgmt/datalake/analytics/account/__init__.py
azure/mgmt/datalake/analytics/account/data_lake_analytics_account_management_client.py
azure/mgmt/datalake/analytics/account/version.py
azure/mgmt/datalake/analytics/account/models/__init__.py
azure/mgmt/datalake/analytics/account/models/add_data_lake_store_parameters.py
azure/mgmt/datalake/analytics/account/models/add_data_lake_store_parameters_py3.py
azure/mgmt/datalake/analytics/account/models/add_data_lake_store_with_account_parameters.py
azure/mgmt/datalake/analytics/account/models/add_data_lake_store_with_account_parameters_py3.py
azure/mgmt/datalake/analytics/account/models/add_storage_account_parameters.py
azure/mgmt/datalake/analytics/account/models/add_storage_account_parameters_py3.py
azure/mgmt/datalake/analytics/account/models/add_storage_account_with_account_parameters.py
azure/mgmt/datalake/analytics/account/models/add_storage_account_with_account_parameters_py3.py
azure/mgmt/datalake/analytics/account/models/capability_information.py
azure/mgmt/datalake/analytics/account/models/capability_information_py3.py
azure/mgmt/datalake/analytics/account/models/check_name_availability_parameters.py
azure/mgmt/datalake/analytics/account/models/check_name_availability_parameters_py3.py
azure/mgmt/datalake/analytics/account/models/compute_policy.py
azure/mgmt/datalake/analytics/account/models/compute_policy_paged.py
azure/mgmt/datalake/analytics/account/models/compute_policy_py3.py
azure/mgmt/datalake/analytics/account/models/create_compute_policy_with_account_parameters.py
azure/mgmt/datalake/analytics/account/models/create_compute_policy_with_account_parameters_py3.py
azure/mgmt/datalake/analytics/account/models/create_data_lake_analytics_account_parameters.py
azure/mgmt/datalake/analytics/account/models/create_data_lake_analytics_account_parameters_py3.py
azure_mgmt_datalake_analytics-0.5.0.dist-info/METADATA
azure_mgmt_datalake_analytics-0.5.0.dist-info/RECORD
azure_mgmt_datalake_analytics-0.5.0.dist-info/WHEEL
azure_mgmt_datalake_analytics-0.5.0.dist-info/top_level.txt
